<?xml version="1.0" encoding="UTF-8"?>
<mxfile host="app.diagrams.net" modified="2026-04-19T10:00:00.000Z" agent="Mozilla/5.0" version="24.0.0">
  <diagram name="Order Sequence Diagram" id="sequence-order-flow">
    <mxGraphModel dx="1200" dy="800" grid="1" gridSize="10" guides="1" tooltips="1" connect="1" arrows="1" fold="1" page="1" pageScale="1" pageWidth="1400" pageHeight="900" background="transparent" math="0" shadow="0">
      <root>
        <mxCell id="0" />
        <mxCell id="1" parent="0" />
        
        <!-- Actors and Objects -->
        <mxCell id="ACTOR-CONSUMER" value="Consumer" style="shape=umlActor;verticalLabelPosition=bottom;verticalAlign=top;html=1;outlineConnect=0;" parent="1" vertex="1">
          <mxGeometry x="50" y="20" width="40" height="60" as="geometry" />
        </mxCell>

        <mxCell id="CONSUMER-APP" value="Consumer App" style="rounded=0;whiteSpace=wrap;html=1;strokeWidth=2;" parent="1" vertex="1">
          <mxGeometry x="30" y="120" width="80" height="50" as="geometry" />
        </mxCell>

        <mxCell id="ORDER-SERVICE" value="Order Service" style="rounded=0;whiteSpace=wrap;html=1;strokeWidth=2;" parent="1" vertex="1">
          <mxGeometry x="190" y="120" width="80" height="50" as="geometry" />
        </mxCell>

        <mxCell id="PAYMENT-SERVICE" value="Payment Service" style="rounded=0;whiteSpace=wrap;html=1;strokeWidth=2;" parent="1" vertex="1">
          <mxGeometry x="350" y="120" width="80" height="50" as="geometry" />
        </mxCell>

        <mxCell id="PAYMENT-GW" value="Payment Gateway" style="rounded=0;whiteSpace=wrap;html=1;strokeWidth=2;" parent="1" vertex="1">
          <mxGeometry x="510" y="120" width="80" height="50" as="geometry" />
        </mxCell>

        <mxCell id="DATABASE" value="Database" style="rounded=0;whiteSpace=wrap;html=1;strokeWidth=2;" parent="1" vertex="1">
          <mxGeometry x="670" y="120" width="80" height="50" as="geometry" />
        </mxCell>

        <mxCell id="NOTIFICATION" value="Notification" style="rounded=0;whiteSpace=wrap;html=1;strokeWidth=2;" parent="1" vertex="1">
          <mxGeometry x="830" y="120" width="80" height="50" as="geometry" />
        </mxCell>

        <mxCell id="ACTOR-FARMER" value="Farmer" style="shape=umlActor;verticalLabelPosition=bottom;verticalAlign=top;html=1;outlineConnect=0;" parent="1" vertex="1">
          <mxGeometry x="970" y="20" width="40" height="60" as="geometry" />
        </mxCell>

        <!-- Lifelines -->
        <mxCell id="LIFELINE-CONSUMER" style="line;strokeWidth=2;dashed=1;" parent="1" edge="1">
          <mxGeometry relative="1" as="geometry">
            <mxPoint x="70" y="80" as="sourcePoint" />
            <mxPoint x="70" y="850" as="targetPoint" />
          </mxGeometry>
        </mxCell>

        <mxCell id="LIFELINE-CONSUMER-APP" style="line;strokeWidth=2;dashed=1;" parent="1" edge="1">
          <mxGeometry relative="1" as="geometry">
            <mxPoint x="70" y="170" as="sourcePoint" />
            <mxPoint x="70" y="850" as="targetPoint" />
          </mxGeometry>
        </mxCell>

        <mxCell id="LIFELINE-ORDER" style="line;strokeWidth=2;dashed=1;" parent="1" edge="1">
          <mxGeometry relative="1" as="geometry">
            <mxPoint x="230" y="170" as="sourcePoint" />
            <mxPoint x="230" y="850" as="targetPoint" />
          </mxGeometry>
        </mxCell>

        <mxCell id="LIFELINE-PAYMENT" style="line;strokeWidth=2;dashed=1;" parent="1" edge="1">
          <mxGeometry relative="1" as="geometry">
            <mxPoint x="390" y="170" as="sourcePoint" />
            <mxPoint x="390" y="850" as="targetPoint" />
          </mxGeometry>
        </mxCell>

        <mxCell id="LIFELINE-GW" style="line;strokeWidth=2;dashed=1;" parent="1" edge="1">
          <mxGeometry relative="1" as="geometry">
            <mxPoint x="550" y="170" as="sourcePoint" />
            <mxPoint x="550" y="850" as="targetPoint" />
          </mxGeometry>
        </mxCell>

        <mxCell id="LIFELINE-DB" style="line;strokeWidth=2;dashed=1;" parent="1" edge="1">
          <mxGeometry relative="1" as="geometry">
            <mxPoint x="710" y="170" as="sourcePoint" />
            <mxPoint x="710" y="850" as="targetPoint" />
          </mxGeometry>
        </mxCell>

        <mxCell id="LIFELINE-NOTIF" style="line;strokeWidth=2;dashed=1;" parent="1" edge="1">
          <mxGeometry relative="1" as="geometry">
            <mxPoint x="870" y="170" as="sourcePoint" />
            <mxPoint x="870" y="850" as="targetPoint" />
          </mxGeometry>
        </mxCell>

        <mxCell id="LIFELINE-FARMER" style="line;strokeWidth=2;dashed=1;" parent="1" edge="1">
          <mxGeometry relative="1" as="geometry">
            <mxPoint x="990" y="80" as="sourcePoint" />
            <mxPoint x="990" y="850" as="targetPoint" />
          </mxGeometry>
        </mxCell>

        <!-- Messages -->
        <!-- Consumer browses products -->
        <mxCell id="MSG1" style="edgeStyle=orthogonalEdgeStyle;rounded=0;orthogonalLoop=1;jettySize=auto;html=1;endArrow=open;startArrow=none;strokeWidth=2;" parent="1" edge="1">
          <mxGeometry relative="1" as="geometry">
            <mxPoint x="70" y="220" as="sourcePoint" />
            <mxPoint x="70" y="220" as="targetPoint" />
          </mxGeometry>
        </mxCell>
        <mxCell id="LABEL1" value="1: Browse Products" style="text;html=1;align=center;verticalAlign=middle;resizable=0;points=[];autosize=1;strokeColor=none;fillColor=none;" parent="1" vertex="1">
          <mxGeometry x="60" y="200" width="120" height="30" as="geometry" />
        </mxCell>

        <!-- Consumer app requests products -->
        <mxCell id="MSG2" style="edgeStyle=orthogonalEdgeStyle;rounded=0;orthogonalLoop=1;jettySize=auto;html=1;endArrow=open;startArrow=none;strokeWidth=2;" parent="1" edge="1">
          <mxGeometry relative="1" as="geometry">
            <mxPoint x="70" y="250" as="sourcePoint" />
            <mxPoint x="190" y="250" as="targetPoint" />
          </mxGeometry>
        </mxCell>
        <mxCell id="LABEL2" value="2: GET /products" style="text;html=1;align=center;verticalAlign=middle;resizable=0;points=[];autosize=1;strokeColor=none;fillColor=none;" parent="1" vertex="1">
          <mxGeometry x="100" y="230" width="100" height="30" as="geometry" />
        </mxCell>

        <!-- Order service queries database -->
        <mxCell id="MSG3" style="edgeStyle=orthogonalEdgeStyle;rounded=0;orthogonalLoop=1;jettySize=auto;html=1;endArrow=open;startArrow=none;strokeWidth=2;" parent="1" edge="1">
          <mxGeometry relative="1" as="geometry">
            <mxPoint x="230" y="280" as="sourcePoint" />
            <mxPoint x="710" y="280" as="targetPoint" />
          </mxGeometry>
        </mxCell>
        <mxCell id="LABEL3" value="3: Query Products" style="text;html=1;align=center;verticalAlign=middle;resizable=0;points=[];autosize=1;strokeColor=none;fillColor=none;" parent="1" vertex="1">
          <mxGeometry x="430" y="260" width="110" height="30" as="geometry" />
        </mxCell>

        <!-- Database returns products -->
        <mxCell id="MSG4" style="edgeStyle=orthogonalEdgeStyle;rounded=0;orthogonalLoop=1;jettySize=auto;html=1;endArrow=open;dashed=1;startArrow=none;strokeWidth=2;" parent="1" edge="1">
          <mxGeometry relative="1" as="geometry">
            <mxPoint x="710" y="310" as="sourcePoint" />
            <mxPoint x="230" y="310" as="targetPoint" />
          </mxGeometry>
        </mxCell>
        <mxCell id="LABEL4" value="4: Product List" style="text;html=1;align=center;verticalAlign=middle;resizable=0;points=[];autosize=1;strokeColor=none;fillColor=none;" parent="1" vertex="1">
          <mxGeometry x="430" y="290" width="110" height="30" as="geometry" />
        </mxCell>

        <!-- Return products to app -->
        <mxCell id="MSG5" style="edgeStyle=orthogonalEdgeStyle;rounded=0;orthogonalLoop=1;jettySize=auto;html=1;endArrow=open;dashed=1;startArrow=none;strokeWidth=2;" parent="1" edge="1">
          <mxGeometry relative="1" as="geometry">
            <mxPoint x="230" y="340" as="sourcePoint" />
            <mxPoint x="70" y="340" as="targetPoint" />
          </mxGeometry>
        </mxCell>
        <mxCell id="LABEL5" value="5: Display Products" style="text;html=1;align=center;verticalAlign=middle;resizable=0;points=[];autosize=1;strokeColor=none;fillColor=none;" parent="1" vertex="1">
          <mxGeometry x="100" y="320" width="110" height="30" as="geometry" />
        </mxCell>

        <!-- Consumer adds to cart -->
        <mxCell id="MSG6" style="edgeStyle=orthogonalEdgeStyle;rounded=0;orthogonalLoop=1;jettySize=auto;html=1;endArrow=open;startArrow=none;strokeWidth=2;" parent="1" edge="1">
          <mxGeometry relative="1" as="geometry">
            <mxPoint x="70" y="380" as="sourcePoint" />
            <mxPoint x="70" y="380" as="targetPoint" />
          </mxGeometry>
        </mxCell>
        <mxCell id="LABEL6" value="6: Add to Cart &amp; Checkout" style="text;html=1;align=center;verticalAlign=middle;resizable=0;points=[];autosize=1;strokeColor=none;fillColor=none;" parent="1" vertex="1">
          <mxGeometry x="50" y="360" width="120" height="30" as="geometry" />
        </mxCell>

        <!-- Create order -->
        <mxCell id="MSG7" style="edgeStyle=orthogonalEdgeStyle;rounded=0;orthogonalLoop=1;jettySize=auto;html=1;endArrow=open;startArrow=none;strokeWidth=2;" parent="1" edge="1">
          <mxGeometry relative="1" as="geometry">
            <mxPoint x="70" y="410" as="sourcePoint" />
            <mxPoint x="230" y="410" as="targetPoint" />
          </mxGeometry>
        </mxCell>
        <mxCell id="LABEL7" value="7: POST /orders" style="text;html=1;align=center;verticalAlign=middle;resizable=0;points=[];autosize=1;strokeColor=none;fillColor=none;" parent="1" vertex="1">
          <mxGeometry x="110" y="390" width="100" height="30" as="geometry" />
        </mxCell>

        <!-- Save order to database -->
        <mxCell id="MSG8" style="edgeStyle=orthogonalEdgeStyle;rounded=0;orthogonalLoop=1;jettySize=auto;html=1;endArrow=open;startArrow=none;strokeWidth=2;" parent="1" edge="1">
          <mxGeometry relative="1" as="geometry">
            <mxPoint x="230" y="440" as="sourcePoint" />
            <mxPoint x="710" y="440" as="targetPoint" />
          </mxGeometry>
        </mxCell>
        <mxCell id="LABEL8" value="8: Save Order" style="text;html=1;align=center;verticalAlign=middle;resizable=0;points=[];autosize=1;strokeColor=none;fillColor=none;" parent="1" vertex="1">
          <mxGeometry x="430" y="420" width="100" height="30" as="geometry" />
        </mxCell>

        <!-- Database confirms -->
        <mxCell id="MSG9" style="edgeStyle=orthogonalEdgeStyle;rounded=0;orthogonalLoop=1;jettySize=auto;html=1;endArrow=open;dashed=1;startArrow=none;strokeWidth=2;" parent="1" edge="1">
          <mxGeometry relative="1" as="geometry">
            <mxPoint x="710" y="470" as="sourcePoint" />
            <mxPoint x="230" y="470" as="targetPoint" />
          </mxGeometry>
        </mxCell>
        <mxCell id="LABEL9" value="9: Order ID" style="text;html=1;align=center;verticalAlign=middle;resizable=0;points=[];autosize=1;strokeColor=none;fillColor=none;" parent="1" vertex="1">
          <mxGeometry x="430" y="450" width="100" height="30" as="geometry" />
        </mxCell>

        <!-- Process payment -->
        <mxCell id="MSG10" style="edgeStyle=orthogonalEdgeStyle;rounded=0;orthogonalLoop=1;jettySize=auto;html=1;endArrow=open;startArrow=none;strokeWidth=2;" parent="1" edge="1">
          <mxGeometry relative="1" as="geometry">
            <mxPoint x="70" y="510" as="sourcePoint" />
            <mxPoint x="390" y="510" as="targetPoint" />
          </mxGeometry>
        </mxCell>
        <mxCell id="LABEL10" value="10: POST /payments" style="text;html=1;align=center;verticalAlign=middle;resizable=0;points=[];autosize=1;strokeColor=none;fillColor=none;" parent="1" vertex="1">
          <mxGeometry x="180" y="490" width="120" height="30" as="geometry" />
        </mxCell>

        <!-- Send to payment gateway -->
        <mxCell id="MSG11" style="edgeStyle=orthogonalEdgeStyle;rounded=0;orthogonalLoop=1;jettySize=auto;html=1;endArrow=open;startArrow=none;strokeWidth=2;" parent="1" edge="1">
          <mxGeometry relative="1" as="geometry">
            <mxPoint x="390" y="540" as="sourcePoint" />
            <mxPoint x="550" y="540" as="targetPoint" />
          </mxGeometry>
        </mxCell>
        <mxCell id="LABEL11" value="11: Process Transaction" style="text;html=1;align=center;verticalAlign=middle;resizable=0;points=[];autosize=1;strokeColor=none;fillColor=none;" parent="1" vertex="1">
          <mxGeometry x="430" y="520" width="120" height="30" as="geometry" />
        </mxCell>

        <!-- Payment result -->
        <mxCell id="MSG12" style="edgeStyle=orthogonalEdgeStyle;rounded=0;orthogonalLoop=1;jettySize=auto;html=1;endArrow=open;dashed=1;startArrow=none;strokeWidth=2;" parent="1" edge="1">
          <mxGeometry relative="1" as="geometry">
            <mxPoint x="550" y="570" as="sourcePoint" />
            <mxPoint x="390" y="570" as="targetPoint" />
          </mxGeometry>
        </mxCell>
        <mxCell id="LABEL12" value="12: Payment Confirmed" style="text;html=1;align=center;verticalAlign=middle;resizable=0;points=[];autosize=1;strokeColor=none;fillColor=none;" parent="1" vertex="1">
          <mxGeometry x="430" y="550" width="120" height="30" as="geometry" />
        </mxCell>

        <!-- Return confirmation -->
        <mxCell id="MSG13" style="edgeStyle=orthogonalEdgeStyle;rounded=0;orthogonalLoop=1;jettySize=auto;html=1;endArrow=open;dashed=1;startArrow=none;strokeWidth=2;" parent="1" edge="1">
          <mxGeometry relative="1" as="geometry">
            <mxPoint x="390" y="600" as="sourcePoint" />
            <mxPoint x="70" y="600" as="targetPoint" />
          </mxGeometry>
        </mxCell>
        <mxCell id="LABEL13" value="13: Payment Confirmed" style="text;html=1;align=center;verticalAlign=middle;resizable=0;points=[];autosize=1;strokeColor=none;fillColor=none;" parent="1" vertex="1">
          <mxGeometry x="180" y="580" width="120" height="30" as="geometry" />
        </mxCell>

        <!-- Update order status -->
        <mxCell id="MSG14" style="edgeStyle=orthogonalEdgeStyle;rounded=0;orthogonalLoop=1;jettySize=auto;html=1;endArrow=open;startArrow=none;strokeWidth=2;" parent="1" edge="1">
          <mxGeometry relative="1" as="geometry">
            <mxPoint x="230" y="630" as="sourcePoint" />
            <mxPoint x="710" y="630" as="targetPoint" />
          </mxGeometry>
        </mxCell>
        <mxCell id="LABEL14" value="14: Update Order" style="text;html=1;align=center;verticalAlign=middle;resizable=0;points=[];autosize=1;strokeColor=none;fillColor=none;" parent="1" vertex="1">
          <mxGeometry x="430" y="610" width="100" height="30" as="geometry" />
        </mxCell>

        <!-- Send notifications -->
        <mxCell id="MSG15" style="edgeStyle=orthogonalEdgeStyle;rounded=0;orthogonalLoop=1;jettySize=auto;html=1;endArrow=open;startArrow=none;strokeWidth=2;" parent="1" edge="1">
          <mxGeometry relative="1" as="geometry">
            <mxPoint x="230" y="660" as="sourcePoint" />
            <mxPoint x="870" y="660" as="targetPoint" />
          </mxGeometry>
        </mxCell>
        <mxCell id="LABEL15" value="15: Send Notifications" style="text;html=1;align=center;verticalAlign=middle;resizable=0;points=[];autosize=1;strokeColor=none;fillColor=none;" parent="1" vertex="1">
          <mxGeometry x="500" y="640" width="120" height="30" as="geometry" />
        </mxCell>

        <!-- Notify consumer -->
        <mxCell id="MSG16" style="edgeStyle=orthogonalEdgeStyle;rounded=0;orthogonalLoop=1;jettySize=auto;html=1;endArrow=open;dashed=1;startArrow=none;strokeWidth=2;" parent="1" edge="1">
          <mxGeometry relative="1" as="geometry">
            <mxPoint x="870" y="690" as="sourcePoint" />
            <mxPoint x="70" y="690" as="targetPoint" />
          </mxGeometry>
        </mxCell>
        <mxCell id="LABEL16" value="16: Order Confirmed Email" style="text;html=1;align=center;verticalAlign=middle;resizable=0;points=[];autosize=1;strokeColor=none;fillColor=none;" parent="1" vertex="1">
          <mxGeometry x="400" y="670" width="130" height="30" as="geometry" />
        </mxCell>

        <!-- Notify farmer -->
        <mxCell id="MSG17" style="edgeStyle=orthogonalEdgeStyle;rounded=0;orthogonalLoop=1;jettySize=auto;html=1;endArrow=open;dashed=1;startArrow=none;strokeWidth=2;" parent="1" edge="1">
          <mxGeometry relative="1" as="geometry">
            <mxPoint x="870" y="720" as="sourcePoint" />
            <mxPoint x="990" y="720" as="targetPoint" />
          </mxGeometry>
        </mxCell>
        <mxCell id="LABEL17" value="17: New Order Notification" style="text;html=1;align=center;verticalAlign=middle;resizable=0;points=[];autosize=1;strokeColor=none;fillColor=none;" parent="1" vertex="1">
          <mxGeometry x="880" y="700" width="130" height="30" as="geometry" />
        </mxCell>

        <!-- Title -->
        <mxCell id="TITLE" value="Order Placement &amp; Payment Flow" style="text;html=1;align=center;fontSize=16;fontStyle=1;strokeColor=none;fillColor=none;" parent="1" vertex="1">
          <mxGeometry x="400" y="10" width="200" height="40" as="geometry" />
        </mxCell>
      </root>
    </mxGraphModel>
  </diagram>
</mxfile>